[
  {
    "studentId": "01hgKu62uL8zAQUu8YQU",
    "studentName": "Dina Molika",
    "username": "N/A",
    "class": "Class 12M",
    "token": "KU8V6DPJVCF2X8P3",
    "qrCodeURL": "https://api.qrserver.com/v1/create-qr-code/?size=300x300&data=https://t.me/rodwell_portal_password_bot?start=KU8V6DPJVCF2X8P3",
    "expiresAt": "2025-08-20T09:35:40.583Z"
  },
  {
    "studentId": "06UKIHNHD8O4M7WcGVEE",
    "studentName": "Mong Martin",
    "username": "N/A",
    "class": "Class 10F",
    "token": "JMJSZK89BWJSGABP",
    "qrCodeURL": "https://api.qrserver.com/v1/create-qr-code/?size=300x300&data=https://t.me/rodwell_portal_password_bot?start=JMJSZK89BWJSGABP",
    "expiresAt": "2025-08-20T09:35:40.584Z"
  },
  {
    "studentId": "09b2i0oZ2byUjqazR4wy",
    "studentName": "Chorn Chanbormey",
    "username": "N/A",
    "class": "Class 12E",
    "token": "RFYDS9S3GEDSCX5N",
    "qrCodeURL": "https://api.qrserver.com/v1/create-qr-code/?size=300x300&data=https://t.me/rodwell_portal_password_bot?start=RFYDS9S3GEDSCX5N",
    "expiresAt": "2025-08-20T09:35:40.584Z"
  },
  {
    "studentId": "0BIrBHN6VYD2hAvvFuvT",
    "studentName": "Kak Kunvorthno",
    "username": "N/A",
    "class": "Class 12I",
    "token": "NAHTFEK244RADMSR",
    "qrCodeURL": "https://api.qrserver.com/v1/create-qr-code/?size=300x300&data=https://t.me/rodwell_portal_password_bot?start=NAHTFEK244RADMSR",
    "expiresAt": "2025-08-20T09:35:40.585Z"
  },
  {
    "studentId": "0GR4lS3h7PZ3cWeK1Baj",
    "studentName": "Simvi Sopheaknita",
    "username": "N/A",
    "class": "Class 11A",
    "token": "VT5EEX5VHB2UFH4C",
    "qrCodeURL": "https://api.qrserver.com/v1/create-qr-code/?size=300x300&data=https://t.me/rodwell_portal_password_bot?start=VT5EEX5VHB2UFH4C",
    "expiresAt": "2025-08-20T09:35:40.585Z"
  },
  {
    "studentId": "0OXsjtOwsWZ4bTmEvt0Y",
    "studentName": "Noun VongVishal",
    "username": "N/A",
    "class": "Class 9E",
    "token": "BXFPU9TT4NKS2ZGR",
    "qrCodeURL": "https://api.qrserver.com/v1/create-qr-code/?size=300x300&data=https://t.me/rodwell_portal_password_bot?start=BXFPU9TT4NKS2ZGR",
    "expiresAt": "2025-08-20T09:35:40.585Z"
  },
  {
    "studentId": "0QRp8BRg4d81WBLdFbqI",
    "studentName": "Phet Sovanreach",
    "username": "N/A",
    "class": "Class 12I",
    "token": "V4EC4ZCES46T4F5C",
    "qrCodeURL": "https://api.qrserver.com/v1/create-qr-code/?size=300x300&data=https://t.me/rodwell_portal_password_bot?start=V4EC4ZCES46T4F5C",
    "expiresAt": "2025-08-20T09:35:40.585Z"
  },
  {
    "studentId": "0aIqAeI6nMX5T1qWjFQt",
    "studentName": "Chea Sokchay",
    "username": "N/A",
    "class": "Class 12E",
    "token": "FMKFKTFQ58UPWU4F",
    "qrCodeURL": "https://api.qrserver.com/v1/create-qr-code/?size=300x300&data=https://t.me/rodwell_portal_password_bot?start=FMKFKTFQ58UPWU4F",
    "expiresAt": "2025-08-20T09:35:40.585Z"
  },
  {
    "studentId": "0gXbbKQtsaoBDpIShDm3",
    "studentName": "Eap Huyly",
    "username": "N/A",
    "class": "Class 12C",
    "token": "ZZEFNEPWN5EMHNV3",
    "qrCodeURL": "https://api.qrserver.com/v1/create-qr-code/?size=300x300&data=https://t.me/rodwell_portal_password_bot?start=ZZEFNEPWN5EMHNV3",
    "expiresAt": "2025-08-20T09:35:40.585Z"
  },
  {
    "studentId": "16IZguyA6xbwzqQt7IG2",
    "studentName": "Soun Dariya",
    "username": "N/A",
    "class": "Class 12C",
    "token": "V5BBEPS8PR3956FD",
    "qrCodeURL": "https://api.qrserver.com/v1/create-qr-code/?size=300x300&data=https://t.me/rodwell_portal_password_bot?start=V5BBEPS8PR3956FD",
    "expiresAt": "2025-08-20T09:35:40.585Z"
  },
  {
    "studentId": "1HQGJNwgftUcLFXIhslp",
    "studentName": "Than ChhayXing",
    "username": "N/A",
    "class": "Class 8E",
    "token": "GGW6Q2V6PSH52PVH",
    "qrCodeURL": "https://api.qrserver.com/v1/create-qr-code/?size=300x300&data=https://t.me/rodwell_portal_password_bot?start=GGW6Q2V6PSH52PVH",
    "expiresAt": "2025-08-20T09:35:40.585Z"
  },
  {
    "studentId": "1KsCYbSpNo2AFYytSniS",
    "studentName": "Houn Kongnoreach",
    "username": "N/A",
    "class": "Class 12M",
    "token": "YYQZ3WVM62DDACBW",
    "qrCodeURL": "https://api.qrserver.com/v1/create-qr-code/?size=300x300&data=https://t.me/rodwell_portal_password_bot?start=YYQZ3WVM62DDACBW",
    "expiresAt": "2025-08-20T09:35:40.585Z"
  },
  {
    "studentId": "1Yrwbkv9IWEgnWBwXtPo",
    "studentName": "Lim Sokviraksal",
    "username": "N/A",
    "class": "Class 9F",
    "token": "9RPQXC4YEPFVBD3R",
    "qrCodeURL": "https://api.qrserver.com/v1/create-qr-code/?size=300x300&data=https://t.me/rodwell_portal_password_bot?start=9RPQXC4YEPFVBD3R",
    "expiresAt": "2025-08-20T09:35:40.586Z"
  },
  {
    "studentId": "1d7nzGQOx9odSrmTlwXA",
    "studentName": "Bo Sereivath",
    "username": "N/A",
    "class": "Class 12I",
    "token": "JBBRWSM56542J37N",
    "qrCodeURL": "https://api.qrserver.com/v1/create-qr-code/?size=300x300&data=https://t.me/rodwell_portal_password_bot?start=JBBRWSM56542J37N",
    "expiresAt": "2025-08-20T09:35:40.586Z"
  },
  {
    "studentId": "1uEQ913jNveL5DgktMNE",
    "studentName": "Chheangly Chheangsour",
    "username": "N/A",
    "class": "Class 12I",
    "token": "V33238UW99L2N4CX",
    "qrCodeURL": "https://api.qrserver.com/v1/create-qr-code/?size=300x300&data=https://t.me/rodwell_portal_password_bot?start=V33238UW99L2N4CX",
    "expiresAt": "2025-08-20T09:35:40.586Z"
  },
  {
    "studentId": "1utUgycRKoo6iFBHUA5Y",
    "studentName": "Taing Eav",
    "username": "N/A",
    "class": "Class 11A",
    "token": "R5SFHT65NXNV58NN",
    "qrCodeURL": "https://api.qrserver.com/v1/create-qr-code/?size=300x300&data=https://t.me/rodwell_portal_password_bot?start=R5SFHT65NXNV58NN",
    "expiresAt": "2025-08-20T09:35:40.586Z"
  },
  {
    "studentId": "2C1HOnDZWTFPH6FNf7Fe",
    "studentName": "Chea MeyY",
    "username": "N/A",
    "class": "Class 12I",
    "token": "36Y9JKTHUXNSXRX2",
    "qrCodeURL": "https://api.qrserver.com/v1/create-qr-code/?size=300x300&data=https://t.me/rodwell_portal_password_bot?start=36Y9JKTHUXNSXRX2",
    "expiresAt": "2025-08-20T09:35:40.586Z"
  },
  {
    "studentId": "2aNSFOTvCCN4oA0364uO",
    "studentName": "Heng Virakkun",
    "username": "N/A",
    "class": "Class 12E",
    "token": "SQ6K9DZQSPNBDVC4",
    "qrCodeURL": "https://api.qrserver.com/v1/create-qr-code/?size=300x300&data=https://t.me/rodwell_portal_password_bot?start=SQ6K9DZQSPNBDVC4",
    "expiresAt": "2025-08-20T09:35:40.586Z"
  },
  {
    "studentId": "2u7YNBpt4RV2WhdIovJ6",
    "studentName": "Kim Monichan",
    "username": "N/A",
    "class": "Class 9F",
    "token": "EJ89SRWYBSP4AU73",
    "qrCodeURL": "https://api.qrserver.com/v1/create-qr-code/?size=300x300&data=https://t.me/rodwell_portal_password_bot?start=EJ89SRWYBSP4AU73",
    "expiresAt": "2025-08-20T09:35:40.586Z"
  },
  {
    "studentId": "33Ln9yaPNS35v5FOc7iF",
    "studentName": "Tei ChhivEang",
    "username": "N/A",
    "class": "Class 12C",
    "token": "SE8TURNKH9WBXT4G",
    "qrCodeURL": "https://api.qrserver.com/v1/create-qr-code/?size=300x300&data=https://t.me/rodwell_portal_password_bot?start=SE8TURNKH9WBXT4G",
    "expiresAt": "2025-08-20T09:35:40.586Z"
  },
  {
    "studentId": "37O7OR2sTCf03clip565",
    "studentName": "Phea Solida",
    "username": "N/A",
    "class": "Class 9E",
    "token": "WUHER9FDPM4WGTTQ",
    "qrCodeURL": "https://api.qrserver.com/v1/create-qr-code/?size=300x300&data=https://t.me/rodwell_portal_password_bot?start=WUHER9FDPM4WGTTQ",
    "expiresAt": "2025-08-20T09:35:40.586Z"
  },
  {
    "studentId": "3fienLE8H1YqgQ1WoSMX",
    "studentName": "Anon Chandanourk",
    "username": "N/A",
    "class": "Class 12I",
    "token": "DGY7L9DW3NRUDUQS",
    "qrCodeURL": "https://api.qrserver.com/v1/create-qr-code/?size=300x300&data=https://t.me/rodwell_portal_password_bot?start=DGY7L9DW3NRUDUQS",
    "expiresAt": "2025-08-20T09:35:40.586Z"
  },
  {
    "studentId": "3ruHZX2WajzAu7vpAcCk",
    "studentName": "Vong Sokreaksmy",
    "username": "N/A",
    "class": "Class 11E",
    "token": "NRGERSGHEGC8WJFA",
    "qrCodeURL": "https://api.qrserver.com/v1/create-qr-code/?size=300x300&data=https://t.me/rodwell_portal_password_bot?start=NRGERSGHEGC8WJFA",
    "expiresAt": "2025-08-20T09:35:40.586Z"
  },
  {
    "studentId": "41v66yM5kJbYbl0J82Jg",
    "studentName": "In Hyzita",
    "username": "N/A",
    "class": "Class 11A",
    "token": "ZMN2XVQNVWJ7UKFB",
    "qrCodeURL": "https://api.qrserver.com/v1/create-qr-code/?size=300x300&data=https://t.me/rodwell_portal_password_bot?start=ZMN2XVQNVWJ7UKFB",
    "expiresAt": "2025-08-20T09:35:40.586Z"
  },
  {
    "studentId": "44vmNBvXlAyLg7joCyfB",
    "studentName": "Khy Kachana",
    "username": "N/A",
    "class": "Class 12E",
    "token": "H5F9VTEUVPBRR26S",
    "qrCodeURL": "https://api.qrserver.com/v1/create-qr-code/?size=300x300&data=https://t.me/rodwell_portal_password_bot?start=H5F9VTEUVPBRR26S",
    "expiresAt": "2025-08-20T09:35:40.586Z"
  },
  {
    "studentId": "44zCLf0NixW58eOsLMnX",
    "studentName": "Srea RattanasaRakpich",
    "username": "N/A",
    "class": "Class 8E",
    "token": "TW7ZKFHRBGUV83SK",
    "qrCodeURL": "https://api.qrserver.com/v1/create-qr-code/?size=300x300&data=https://t.me/rodwell_portal_password_bot?start=TW7ZKFHRBGUV83SK",
    "expiresAt": "2025-08-20T09:35:40.586Z"
  },
  {
    "studentId": "4RPr5w3rPRs3MIQ5zJCI",
    "studentName": "You Sopheakpanhavatey",
    "username": "N/A",
    "class": "Class 10F",
    "token": "P6BHTXYQD6K33KFG",
    "qrCodeURL": "https://api.qrserver.com/v1/create-qr-code/?size=300x300&data=https://t.me/rodwell_portal_password_bot?start=P6BHTXYQD6K33KFG",
    "expiresAt": "2025-08-20T09:35:40.586Z"
  },
  {
    "studentId": "4reqrABRzDZmVj1ny4N4",
    "studentName": "Taing Samnang",
    "username": "N/A",
    "class": "Class 12E",
    "token": "KJLJKQLN75E3WHM5",
    "qrCodeURL": "https://api.qrserver.com/v1/create-qr-code/?size=300x300&data=https://t.me/rodwell_portal_password_bot?start=KJLJKQLN75E3WHM5",
    "expiresAt": "2025-08-20T09:35:40.586Z"
  },
  {
    "studentId": "5bkd8dkoQItMdWhcl7jM",
    "studentName": "Ny ChansokthyRath",
    "username": "N/A",
    "class": "Class 8E",
    "token": "9RPLGL4DPG8J94FD",
    "qrCodeURL": "https://api.qrserver.com/v1/create-qr-code/?size=300x300&data=https://t.me/rodwell_portal_password_bot?start=9RPLGL4DPG8J94FD",
    "expiresAt": "2025-08-20T09:35:40.586Z"
  },
  {
    "studentId": "5jaKWoMTJNAbFJNRISOL",
    "studentName": "Eav Yeanchhing",
    "username": "N/A",
    "class": "Class 11E",
    "token": "E3U5MESFKW44BQNV",
    "qrCodeURL": "https://api.qrserver.com/v1/create-qr-code/?size=300x300&data=https://t.me/rodwell_portal_password_bot?start=E3U5MESFKW44BQNV",
    "expiresAt": "2025-08-20T09:35:40.586Z"
  },
  {
    "studentId": "5oB28GetSnIsDgRLk4gg",
    "studentName": "Duong Toeuyeak",
    "username": "N/A",
    "class": "Class 12C",
    "token": "7QXXSVPRK35E6FGC",
    "qrCodeURL": "https://api.qrserver.com/v1/create-qr-code/?size=300x300&data=https://t.me/rodwell_portal_password_bot?start=7QXXSVPRK35E6FGC",
    "expiresAt": "2025-08-20T09:35:40.587Z"
  },
  {
    "studentId": "6MT5CRzvC2E65uXtUjgE",
    "studentName": "Lang Voleak",
    "username": "N/A",
    "class": "Class 12S",
    "token": "VP8VNBSCQ4VDNYGK",
    "qrCodeURL": "https://api.qrserver.com/v1/create-qr-code/?size=300x300&data=https://t.me/rodwell_portal_password_bot?start=VP8VNBSCQ4VDNYGK",
    "expiresAt": "2025-08-20T09:35:40.587Z"
  },
  {
    "studentId": "6UhykcIRUB1ASzGHVdX5",
    "studentName": "Hak Sivfong",
    "username": "N/A",
    "class": "Class 12C",
    "token": "R6Z26GHZXQXXVUYP",
    "qrCodeURL": "https://api.qrserver.com/v1/create-qr-code/?size=300x300&data=https://t.me/rodwell_portal_password_bot?start=R6Z26GHZXQXXVUYP",
    "expiresAt": "2025-08-20T09:35:40.587Z"
  },
  {
    "studentId": "6Y1P8wcXhCHKiwtKyy7T",
    "studentName": "Pek Sopheaktra",
    "username": "N/A",
    "class": "Class 11E",
    "token": "5Q234BK7CX8ZTP3P",
    "qrCodeURL": "https://api.qrserver.com/v1/create-qr-code/?size=300x300&data=https://t.me/rodwell_portal_password_bot?start=5Q234BK7CX8ZTP3P",
    "expiresAt": "2025-08-20T09:35:40.587Z"
  },
  {
    "studentId": "6da9bRVNeLmGlLoJsyCH",
    "studentName": "Soeu Dalex",
    "username": "N/A",
    "class": "Class 12I",
    "token": "HY42NGQYMLDU73ZW",
    "qrCodeURL": "https://api.qrserver.com/v1/create-qr-code/?size=300x300&data=https://t.me/rodwell_portal_password_bot?start=HY42NGQYMLDU73ZW",
    "expiresAt": "2025-08-20T09:35:40.587Z"
  },
  {
    "studentId": "8o1XD7WqktF4zsosZ3Fj",
    "studentName": "Kong Hanchhay",
    "username": "N/A",
    "class": "Class 7E",
    "token": "7JMCESKLKMPUE8U3",
    "qrCodeURL": "https://api.qrserver.com/v1/create-qr-code/?size=300x300&data=https://t.me/rodwell_portal_password_bot?start=7JMCESKLKMPUE8U3",
    "expiresAt": "2025-08-20T09:35:40.587Z"
  },
  {
    "studentId": "9Ew0aAXuWdUu16isd1ZX",
    "studentName": "Chea Chanreaksa",
    "username": "N/A",
    "class": "Class 11E",
    "token": "LFF2AYBDDS6KSDCW",
    "qrCodeURL": "https://api.qrserver.com/v1/create-qr-code/?size=300x300&data=https://t.me/rodwell_portal_password_bot?start=LFF2AYBDDS6KSDCW",
    "expiresAt": "2025-08-20T09:35:40.587Z"
  },
  {
    "studentId": "9dtGTAYgwagS4oLRWI9M",
    "studentName": "Chanda Mady",
    "username": "N/A",
    "class": "Class 12C",
    "token": "6F7X65HEUZW4A9X8",
    "qrCodeURL": "https://api.qrserver.com/v1/create-qr-code/?size=300x300&data=https://t.me/rodwell_portal_password_bot?start=6F7X65HEUZW4A9X8",
    "expiresAt": "2025-08-20T09:35:40.587Z"
  },
  {
    "studentId": "A0M1wJnle0fanMl5ftlc",
    "studentName": "Ly Thonghay",
    "username": "N/A",
    "class": "Class 11E",
    "token": "NJER7GGDSBJRCFEC",
    "qrCodeURL": "https://api.qrserver.com/v1/create-qr-code/?size=300x300&data=https://t.me/rodwell_portal_password_bot?start=NJER7GGDSBJRCFEC",
    "expiresAt": "2025-08-20T09:35:40.587Z"
  },
  {
    "studentId": "AnCloe0hy7l8IxCSdMaJ",
    "studentName": "Sophat Sophanan",
    "username": "N/A",
    "class": "Class 8E",
    "token": "QMKUBW4R59M56UHX",
    "qrCodeURL": "https://api.qrserver.com/v1/create-qr-code/?size=300x300&data=https://t.me/rodwell_portal_password_bot?start=QMKUBW4R59M56UHX",
    "expiresAt": "2025-08-20T09:35:40.587Z"
  },
  {
    "studentId": "ApoJLnMTQ33QNjyW2UHa",
    "studentName": "Sam VattanakViseth",
    "username": "N/A",
    "class": "Class 11E",
    "token": "XEX6R2RY53K8UWYE",
    "qrCodeURL": "https://api.qrserver.com/v1/create-qr-code/?size=300x300&data=https://t.me/rodwell_portal_password_bot?start=XEX6R2RY53K8UWYE",
    "expiresAt": "2025-08-20T09:35:40.587Z"
  },
  {
    "studentId": "AyVAKHgbhvZJLk3W7Ic3",
    "studentName": "Pich Thida",
    "username": "N/A",
    "class": "Class 8E",
    "token": "UEWYEY6Z9JFDDDUZ",
    "qrCodeURL": "https://api.qrserver.com/v1/create-qr-code/?size=300x300&data=https://t.me/rodwell_portal_password_bot?start=UEWYEY6Z9JFDDDUZ",
    "expiresAt": "2025-08-20T09:35:40.587Z"
  },
  {
    "studentId": "BG3VMnmNK8hZFTurzmpd",
    "studentName": "Ross K-Ro",
    "username": "N/A",
    "class": "Class 12I",
    "token": "R2D28J9YQMCAZMA8",
    "qrCodeURL": "https://api.qrserver.com/v1/create-qr-code/?size=300x300&data=https://t.me/rodwell_portal_password_bot?start=R2D28J9YQMCAZMA8",
    "expiresAt": "2025-08-20T09:35:40.587Z"
  },
  {
    "studentId": "BROrXmuQDza0Xx3x8rZc",
    "studentName": "Lim Lysethika",
    "username": "N/A",
    "class": "Class 11A",
    "token": "6RGXWLPWLQ3HGM6E",
    "qrCodeURL": "https://api.qrserver.com/v1/create-qr-code/?size=300x300&data=https://t.me/rodwell_portal_password_bot?start=6RGXWLPWLQ3HGM6E",
    "expiresAt": "2025-08-20T09:35:40.587Z"
  },
  {
    "studentId": "BlKD5htPzEeCvQcpuqim",
    "studentName": "Prak Sopanha",
    "username": "N/A",
    "class": "Class 12C",
    "token": "4RCVH3NDNPGST2KG",
    "qrCodeURL": "https://api.qrserver.com/v1/create-qr-code/?size=300x300&data=https://t.me/rodwell_portal_password_bot?start=4RCVH3NDNPGST2KG",
    "expiresAt": "2025-08-20T09:35:40.587Z"
  },
  {
    "studentId": "CAMMl6A6ewoBrn4iOAEq",
    "studentName": "Nhem Pichet",
    "username": "N/A",
    "class": "Class 10F",
    "token": "Z5M5Z6MHAGPK7EYU",
    "qrCodeURL": "https://api.qrserver.com/v1/create-qr-code/?size=300x300&data=https://t.me/rodwell_portal_password_bot?start=Z5M5Z6MHAGPK7EYU",
    "expiresAt": "2025-08-20T09:35:40.587Z"
  },
  {
    "studentId": "CWkkSLh7OknrUz8hUbdj",
    "studentName": "Meng SereySirayuth",
    "username": "N/A",
    "class": "Class 11E",
    "token": "HVZ5V7VXQJJXKLP5",
    "qrCodeURL": "https://api.qrserver.com/v1/create-qr-code/?size=300x300&data=https://t.me/rodwell_portal_password_bot?start=HVZ5V7VXQJJXKLP5",
    "expiresAt": "2025-08-20T09:35:40.587Z"
  },
  {
    "studentId": "Cf2M2qbHU8Ciy3K6RyVE",
    "studentName": "Ren Bothireach",
    "username": "N/A",
    "class": "Class 8E",
    "token": "VFTT4CPGWRTCB75C",
    "qrCodeURL": "https://api.qrserver.com/v1/create-qr-code/?size=300x300&data=https://t.me/rodwell_portal_password_bot?start=VFTT4CPGWRTCB75C",
    "expiresAt": "2025-08-20T09:35:40.587Z"
  },
  {
    "studentId": "D1XcQTPCjPvtEy4eouv1",
    "studentName": "Sao Sivmeili",
    "username": "N/A",
    "class": "Class 8E",
    "token": "LP5D96JWJKQWQM4E",
    "qrCodeURL": "https://api.qrserver.com/v1/create-qr-code/?size=300x300&data=https://t.me/rodwell_portal_password_bot?start=LP5D96JWJKQWQM4E",
    "expiresAt": "2025-08-20T09:35:40.587Z"
  },
  {
    "studentId": "DERdKzvJRQKExsbb4Ffa",
    "studentName": "Pho Lysoukim",
    "username": "N/A",
    "class": "Class 12C",
    "token": "8EYRR8M3E4JKZAAJ",
    "qrCodeURL": "https://api.qrserver.com/v1/create-qr-code/?size=300x300&data=https://t.me/rodwell_portal_password_bot?start=8EYRR8M3E4JKZAAJ",
    "expiresAt": "2025-08-20T09:35:40.587Z"
  },
  {
    "studentId": "DrL84ZlndGGzchkcE5bB",
    "studentName": "Phors Vouchleap",
    "username": "N/A",
    "class": "Class 11A",
    "token": "S6TVDRX2DAESDF3Q",
    "qrCodeURL": "https://api.qrserver.com/v1/create-qr-code/?size=300x300&data=https://t.me/rodwell_portal_password_bot?start=S6TVDRX2DAESDF3Q",
    "expiresAt": "2025-08-20T09:35:40.587Z"
  },
  {
    "studentId": "ENCtO8Dr5YpjHn5aDXFF",
    "studentName": "Kann Monineath",
    "username": "N/A",
    "class": "Class 9E",
    "token": "PQBW43TTW8B6DVK6",
    "qrCodeURL": "https://api.qrserver.com/v1/create-qr-code/?size=300x300&data=https://t.me/rodwell_portal_password_bot?start=PQBW43TTW8B6DVK6",
    "expiresAt": "2025-08-20T09:35:40.587Z"
  },
  {
    "studentId": "GF64OJqvYHnmuI42epsf",
    "studentName": "Mony Vichita",
    "username": "N/A",
    "class": "Class 12NKGS",
    "token": "TXHFP3E9NJ54HZJC",
    "qrCodeURL": "https://api.qrserver.com/v1/create-qr-code/?size=300x300&data=https://t.me/rodwell_portal_password_bot?start=TXHFP3E9NJ54HZJC",
    "expiresAt": "2025-08-20T09:35:40.587Z"
  },
  {
    "studentId": "GFIypIif7T3qGYSQ6aZ9",
    "studentName": "Sok ChanMeyjing",
    "username": "N/A",
    "class": "Class 9E",
    "token": "7Y9HQ857ERHCWQGG",
    "qrCodeURL": "https://api.qrserver.com/v1/create-qr-code/?size=300x300&data=https://t.me/rodwell_portal_password_bot?start=7Y9HQ857ERHCWQGG",
    "expiresAt": "2025-08-20T09:35:40.587Z"
  },
  {
    "studentId": "GHqxaSoKp933We6UpFZg",
    "studentName": "In Hytepy",
    "username": "N/A",
    "class": "Class 10F",
    "token": "JZU76XWC6M78HF92",
    "qrCodeURL": "https://api.qrserver.com/v1/create-qr-code/?size=300x300&data=https://t.me/rodwell_portal_password_bot?start=JZU76XWC6M78HF92",
    "expiresAt": "2025-08-20T09:35:40.587Z"
  },
  {
    "studentId": "GQUG4Ubl4hQVY0AYTNh0",
    "studentName": "Nhem Sokmongkol",
    "username": "N/A",
    "class": "Class 12M",
    "token": "8BZAX2RYQA88ELUY",
    "qrCodeURL": "https://api.qrserver.com/v1/create-qr-code/?size=300x300&data=https://t.me/rodwell_portal_password_bot?start=8BZAX2RYQA88ELUY",
    "expiresAt": "2025-08-20T09:35:40.587Z"
  },
  {
    "studentId": "GZorw0hErUI5EG48gHx6",
    "studentName": "Hoeun Keochanpisey",
    "username": "N/A",
    "class": "Class 9F",
    "token": "8AE6WKNWMHYE42MQ",
    "qrCodeURL": "https://api.qrserver.com/v1/create-qr-code/?size=300x300&data=https://t.me/rodwell_portal_password_bot?start=8AE6WKNWMHYE42MQ",
    "expiresAt": "2025-08-20T09:35:40.587Z"
  },
  {
    "studentId": "Gh8zIKdPtovsnyO0GNfT",
    "studentName": "Nal Oudom",
    "username": "N/A",
    "class": "Class 9F",
    "token": "ABDTG7QEH7ZJ8ERN",
    "qrCodeURL": "https://api.qrserver.com/v1/create-qr-code/?size=300x300&data=https://t.me/rodwell_portal_password_bot?start=ABDTG7QEH7ZJ8ERN",
    "expiresAt": "2025-08-20T09:35:40.587Z"
  },
  {
    "studentId": "HNTD9yMki9w6HqOsbsUE",
    "studentName": "Chhay Thaiheng",
    "username": "N/A",
    "class": "Class 10E",
    "token": "YL4QP823SA8RMHSM",
    "qrCodeURL": "https://api.qrserver.com/v1/create-qr-code/?size=300x300&data=https://t.me/rodwell_portal_password_bot?start=YL4QP823SA8RMHSM",
    "expiresAt": "2025-08-20T09:35:40.587Z"
  },
  {
    "studentId": "HzsS1Kl2yThMfqRLAscq",
    "studentName": "Khov PechChetra",
    "username": "khovpechchetra327",
    "class": "Class 7E",
    "token": "WDLVRHFS6YQVJL65",
    "qrCodeURL": "https://api.qrserver.com/v1/create-qr-code/?size=300x300&data=https://t.me/rodwell_portal_password_bot?start=WDLVRHFS6YQVJL65",
    "expiresAt": "2025-08-20T09:35:40.587Z"
  },
  {
    "studentId": "I1NdaZL1GWEwUGkKhHjL",
    "studentName": "Kheang Susean",
    "username": "N/A",
    "class": "Class 12E",
    "token": "6GXFAAYAXYH6HULP",
    "qrCodeURL": "https://api.qrserver.com/v1/create-qr-code/?size=300x300&data=https://t.me/rodwell_portal_password_bot?start=6GXFAAYAXYH6HULP",
    "expiresAt": "2025-08-20T09:35:40.588Z"
  },
  {
    "studentId": "IZ1NOSc1sXZUDdMKvdBm",
    "studentName": "Tao Sokretmony",
    "username": "N/A",
    "class": "Class 12NKGS",
    "token": "PH57AMJKD7AXEXAV",
    "qrCodeURL": "https://api.qrserver.com/v1/create-qr-code/?size=300x300&data=https://t.me/rodwell_portal_password_bot?start=PH57AMJKD7AXEXAV",
    "expiresAt": "2025-08-20T09:35:40.588Z"
  },
  {
    "studentId": "Iz8gu2Qx39qk6Sf0JyAa",
    "studentName": "Kem Odamvuttey",
    "username": "N/A",
    "class": "Class 12S",
    "token": "ZMS6WRNFHFBSPWEX",
    "qrCodeURL": "https://api.qrserver.com/v1/create-qr-code/?size=300x300&data=https://t.me/rodwell_portal_password_bot?start=ZMS6WRNFHFBSPWEX",
    "expiresAt": "2025-08-20T09:35:40.588Z"
  },
  {
    "studentId": "JfE2clKNdP9Idha2jtPW",
    "studentName": "Vey Pichmaliny",
    "username": "N/A",
    "class": "Class 12E",
    "token": "BL7VQR8ZUGSMVANL",
    "qrCodeURL": "https://api.qrserver.com/v1/create-qr-code/?size=300x300&data=https://t.me/rodwell_portal_password_bot?start=BL7VQR8ZUGSMVANL",
    "expiresAt": "2025-08-20T09:35:40.588Z"
  },
  {
    "studentId": "KdtfftiXOZmnqxA5FgYv",
    "studentName": "So Liza",
    "username": "N/A",
    "class": "Class 12C",
    "token": "2RSWQ66AB7CJYQT8",
    "qrCodeURL": "https://api.qrserver.com/v1/create-qr-code/?size=300x300&data=https://t.me/rodwell_portal_password_bot?start=2RSWQ66AB7CJYQT8",
    "expiresAt": "2025-08-20T09:35:40.588Z"
  },
  {
    "studentId": "KoqspNpUol5dRgFOKeqq",
    "studentName": "Y Seavhour",
    "username": "N/A",
    "class": "Class 11E",
    "token": "CKFZDAWM4RGW85T7",
    "qrCodeURL": "https://api.qrserver.com/v1/create-qr-code/?size=300x300&data=https://t.me/rodwell_portal_password_bot?start=CKFZDAWM4RGW85T7",
    "expiresAt": "2025-08-20T09:35:40.588Z"
  },
  {
    "studentId": "L0j4vTyH7qL7rUlwpKf4",
    "studentName": "Heng ChiTek",
    "username": "N/A",
    "class": "Class 12I",
    "token": "JJ7QJSBMTN8ACLCU",
    "qrCodeURL": "https://api.qrserver.com/v1/create-qr-code/?size=300x300&data=https://t.me/rodwell_portal_password_bot?start=JJ7QJSBMTN8ACLCU",
    "expiresAt": "2025-08-20T09:35:40.588Z"
  },
  {
    "studentId": "L21ttJcwPIpet6juO4ZF",
    "studentName": "Reth Rechborneath",
    "username": "N/A",
    "class": "Class 12I",
    "token": "6Q4X8T36E5N99KTF",
    "qrCodeURL": "https://api.qrserver.com/v1/create-qr-code/?size=300x300&data=https://t.me/rodwell_portal_password_bot?start=6Q4X8T36E5N99KTF",
    "expiresAt": "2025-08-20T09:35:40.588Z"
  },
  {
    "studentId": "LAyeHZMi6qpZF39XF5lA",
    "studentName": "Khat Sovanpanha",
    "username": "N/A",
    "class": "Class 12NKGS",
    "token": "AM5BERY489WS5SRK",
    "qrCodeURL": "https://api.qrserver.com/v1/create-qr-code/?size=300x300&data=https://t.me/rodwell_portal_password_bot?start=AM5BERY489WS5SRK",
    "expiresAt": "2025-08-20T09:35:40.588Z"
  },
  {
    "studentId": "LM6UHAhc83N1qZ3pm7W8",
    "studentName": "Kea Sreyheng",
    "username": "N/A",
    "class": "Class 12M",
    "token": "ZVSCASZ8CQTLG55A",
    "qrCodeURL": "https://api.qrserver.com/v1/create-qr-code/?size=300x300&data=https://t.me/rodwell_portal_password_bot?start=ZVSCASZ8CQTLG55A",
    "expiresAt": "2025-08-20T09:35:40.588Z"
  },
  {
    "studentId": "LuyZ4PmZ0yTDeiuZ4Q4A",
    "studentName": "Sinh Narong",
    "username": "N/A",
    "class": "Class 9E",
    "token": "JJTVM8PZ97DDNJUS",
    "qrCodeURL": "https://api.qrserver.com/v1/create-qr-code/?size=300x300&data=https://t.me/rodwell_portal_password_bot?start=JJTVM8PZ97DDNJUS",
    "expiresAt": "2025-08-20T09:35:40.588Z"
  },
  {
    "studentId": "Lx0SmylZWPytX8bjJMeB",
    "studentName": "Rath Sokleap",
    "username": "N/A",
    "class": "Class 12M",
    "token": "KUJNSVYCXK8SKN48",
    "qrCodeURL": "https://api.qrserver.com/v1/create-qr-code/?size=300x300&data=https://t.me/rodwell_portal_password_bot?start=KUJNSVYCXK8SKN48",
    "expiresAt": "2025-08-20T09:35:40.588Z"
  },
  {
    "studentId": "Mj8HAXHZuFJ0Qlzkvs2z",
    "studentName": "Rin Mana",
    "username": "N/A",
    "class": "Class 12S",
    "token": "2V47ZMJA8YVDWVJF",
    "qrCodeURL": "https://api.qrserver.com/v1/create-qr-code/?size=300x300&data=https://t.me/rodwell_portal_password_bot?start=2V47ZMJA8YVDWVJF",
    "expiresAt": "2025-08-20T09:35:40.588Z"
  },
  {
    "studentId": "MxgIVhuecRXNWWtkJxzB",
    "studentName": "Try Socheata",
    "username": "N/A",
    "class": "Class 11A",
    "token": "EHVBZKXNT4S4YQ68",
    "qrCodeURL": "https://api.qrserver.com/v1/create-qr-code/?size=300x300&data=https://t.me/rodwell_portal_password_bot?start=EHVBZKXNT4S4YQ68",
    "expiresAt": "2025-08-20T09:35:40.588Z"
  },
  {
    "studentId": "NEZRF0MGCpeX6UGubFq6",
    "studentName": "Mech Penhbormey",
    "username": "N/A",
    "class": "Class 11E",
    "token": "HXUW6WBJ3Q4ARJQ7",
    "qrCodeURL": "https://api.qrserver.com/v1/create-qr-code/?size=300x300&data=https://t.me/rodwell_portal_password_bot?start=HXUW6WBJ3Q4ARJQ7",
    "expiresAt": "2025-08-20T09:35:40.588Z"
  },
  {
    "studentId": "O05sDTm8CHg4o8DcyyT2",
    "studentName": "Bun Sivyean",
    "username": "N/A",
    "class": "Class 12S",
    "token": "W3RALEQE2D6MHF3C",
    "qrCodeURL": "https://api.qrserver.com/v1/create-qr-code/?size=300x300&data=https://t.me/rodwell_portal_password_bot?start=W3RALEQE2D6MHF3C",
    "expiresAt": "2025-08-20T09:35:40.588Z"
  },
  {
    "studentId": "O1pKkop3xNOqoZlQo8Pa",
    "studentName": "Saruth Vuthika",
    "username": "N/A",
    "class": "Class 12S",
    "token": "RH4ANMP9CY9QFEZ4",
    "qrCodeURL": "https://api.qrserver.com/v1/create-qr-code/?size=300x300&data=https://t.me/rodwell_portal_password_bot?start=RH4ANMP9CY9QFEZ4",
    "expiresAt": "2025-08-20T09:35:40.588Z"
  },
  {
    "studentId": "O1rm0qKQB7qt5uxpE4WT",
    "studentName": "Heng Mouyhorng",
    "username": "N/A",
    "class": "Class 10E",
    "token": "GE8MF9XWSTR4YAFV",
    "qrCodeURL": "https://api.qrserver.com/v1/create-qr-code/?size=300x300&data=https://t.me/rodwell_portal_password_bot?start=GE8MF9XWSTR4YAFV",
    "expiresAt": "2025-08-20T09:35:40.588Z"
  },
  {
    "studentId": "OFb272tq8hUIFcL01ddU",
    "studentName": "Theng DyLyJames",
    "username": "N/A",
    "class": "Class 12M",
    "token": "JWVRAHJW82LMCT3G",
    "qrCodeURL": "https://api.qrserver.com/v1/create-qr-code/?size=300x300&data=https://t.me/rodwell_portal_password_bot?start=JWVRAHJW82LMCT3G",
    "expiresAt": "2025-08-20T09:35:40.588Z"
  },
  {
    "studentId": "OR8KUBnocQJWtqE0wFkK",
    "studentName": "Sear SarikKnika",
    "username": "N/A",
    "class": "Class 12S",
    "token": "CBZCW5RBSRH7XAHH",
    "qrCodeURL": "https://api.qrserver.com/v1/create-qr-code/?size=300x300&data=https://t.me/rodwell_portal_password_bot?start=CBZCW5RBSRH7XAHH",
    "expiresAt": "2025-08-20T09:35:40.588Z"
  },
  {
    "studentId": "OTQBW8nl3ma2ez9NmRnk",
    "studentName": "Eang Virakvattanac",
    "username": "N/A",
    "class": "Class 7E",
    "token": "TT49FLTAFSL9R4XQ",
    "qrCodeURL": "https://api.qrserver.com/v1/create-qr-code/?size=300x300&data=https://t.me/rodwell_portal_password_bot?start=TT49FLTAFSL9R4XQ",
    "expiresAt": "2025-08-20T09:35:40.588Z"
  },
  {
    "studentId": "OWhFfacjtSguTqBVjppn",
    "studentName": "Hong Leeheng",
    "username": "N/A",
    "class": "Class 12I",
    "token": "GTMYN9DYLU9X59HD",
    "qrCodeURL": "https://api.qrserver.com/v1/create-qr-code/?size=300x300&data=https://t.me/rodwell_portal_password_bot?start=GTMYN9DYLU9X59HD",
    "expiresAt": "2025-08-20T09:35:40.588Z"
  },
  {
    "studentId": "OXiEd7QulDMSFEZ8XUbo",
    "studentName": "Chea Somanith",
    "username": "N/A",
    "class": "Class 12C",
    "token": "2A9PYK38MPX67BS5",
    "qrCodeURL": "https://api.qrserver.com/v1/create-qr-code/?size=300x300&data=https://t.me/rodwell_portal_password_bot?start=2A9PYK38MPX67BS5",
    "expiresAt": "2025-08-20T09:35:40.588Z"
  },
  {
    "studentId": "Os4utUpNSeJoCAPeVrr6",
    "studentName": "Doeun VannakMolinet",
    "username": "N/A",
    "class": "Class 12C",
    "token": "YQJUERYPU496N23S",
    "qrCodeURL": "https://api.qrserver.com/v1/create-qr-code/?size=300x300&data=https://t.me/rodwell_portal_password_bot?start=YQJUERYPU496N23S",
    "expiresAt": "2025-08-20T09:35:40.588Z"
  },
  {
    "studentId": "OwVekPD0GkILBKnAzRUK",
    "studentName": "Koemsinh Sochheka",
    "username": "N/A",
    "class": "Class 12M",
    "token": "LK938JBABB6S3F86",
    "qrCodeURL": "https://api.qrserver.com/v1/create-qr-code/?size=300x300&data=https://t.me/rodwell_portal_password_bot?start=LK938JBABB6S3F86",
    "expiresAt": "2025-08-20T09:35:40.588Z"
  },
  {
    "studentId": "Ox4qT27YS53WJJSOdV0i",
    "studentName": "Ly Thavrakbuth",
    "username": "N/A",
    "class": "Class 12NKGS",
    "token": "MGT6YKLE7FK66RXP",
    "qrCodeURL": "https://api.qrserver.com/v1/create-qr-code/?size=300x300&data=https://t.me/rodwell_portal_password_bot?start=MGT6YKLE7FK66RXP",
    "expiresAt": "2025-08-20T09:35:40.588Z"
  },
  {
    "studentId": "P41vrhxAG62aVrUnSMgb",
    "studentName": "Chea Rosa",
    "username": "N/A",
    "class": "Class 9E",
    "token": "8BBQEBFRENBNMG8K",
    "qrCodeURL": "https://api.qrserver.com/v1/create-qr-code/?size=300x300&data=https://t.me/rodwell_portal_password_bot?start=8BBQEBFRENBNMG8K",
    "expiresAt": "2025-08-20T09:35:40.588Z"
  },
  {
    "studentId": "PcDLXExcdTA321LC49nr",
    "studentName": "Na Lyteang",
    "username": "N/A",
    "class": "Class 7E",
    "token": "NPKU9BB4BV58MK3Z",
    "qrCodeURL": "https://api.qrserver.com/v1/create-qr-code/?size=300x300&data=https://t.me/rodwell_portal_password_bot?start=NPKU9BB4BV58MK3Z",
    "expiresAt": "2025-08-20T09:35:40.588Z"
  },
  {
    "studentId": "PgUKI9WQDG6yTmzt2PWx",
    "studentName": "Ly Sonisa",
    "username": "N/A",
    "class": "Class 12M",
    "token": "GSA6TWAU5NSAA3U2",
    "qrCodeURL": "https://api.qrserver.com/v1/create-qr-code/?size=300x300&data=https://t.me/rodwell_portal_password_bot?start=GSA6TWAU5NSAA3U2",
    "expiresAt": "2025-08-20T09:35:40.588Z"
  },
  {
    "studentId": "QRF5TOa7eUVmQ9qgDcNh",
    "studentName": "Toun Kornsethawin",
    "username": "N/A",
    "class": "Class 12I",
    "token": "X8UZD2LBCDJP46QA",
    "qrCodeURL": "https://api.qrserver.com/v1/create-qr-code/?size=300x300&data=https://t.me/rodwell_portal_password_bot?start=X8UZD2LBCDJP46QA",
    "expiresAt": "2025-08-20T09:35:40.588Z"
  },
  {
    "studentId": "Qdbkln2azk3CtcY2rBCx",
    "studentName": "Veng Khayheng",
    "username": "N/A",
    "class": "Class 12I",
    "token": "7W5ZD6Z5YECT2TNT",
    "qrCodeURL": "https://api.qrserver.com/v1/create-qr-code/?size=300x300&data=https://t.me/rodwell_portal_password_bot?start=7W5ZD6Z5YECT2TNT",
    "expiresAt": "2025-08-20T09:35:40.588Z"
  },
  {
    "studentId": "QgTxzJecOJU40w9g0FXB",
    "studentName": "Thai Kimheang",
    "username": "N/A",
    "class": "Class 12C",
    "token": "JHKUK3RVX9WH5K3C",
    "qrCodeURL": "https://api.qrserver.com/v1/create-qr-code/?size=300x300&data=https://t.me/rodwell_portal_password_bot?start=JHKUK3RVX9WH5K3C",
    "expiresAt": "2025-08-20T09:35:40.589Z"
  },
  {
    "studentId": "QiBRzV44oqmNbWw9XBz8",
    "studentName": "Oeun Loy",
    "username": "N/A",
    "class": "Class 11E",
    "token": "UZ9M95GPVUWMMDKN",
    "qrCodeURL": "https://api.qrserver.com/v1/create-qr-code/?size=300x300&data=https://t.me/rodwell_portal_password_bot?start=UZ9M95GPVUWMMDKN",
    "expiresAt": "2025-08-20T09:35:40.589Z"
  },
  {
    "studentId": "R0uVROTT5a0xS7sdiwsf",
    "studentName": "Eay Dara",
    "username": "N/A",
    "class": "Class 12I",
    "token": "WJHMXSVYR4HJZXBM",
    "qrCodeURL": "https://api.qrserver.com/v1/create-qr-code/?size=300x300&data=https://t.me/rodwell_portal_password_bot?start=WJHMXSVYR4HJZXBM",
    "expiresAt": "2025-08-20T09:35:40.589Z"
  },
  {
    "studentId": "RGfpEx6eyeJKympi2qdI",
    "studentName": "Im Kimleng",
    "username": "N/A",
    "class": "Class 8E",
    "token": "T4T9K9TF87D8MW3K",
    "qrCodeURL": "https://api.qrserver.com/v1/create-qr-code/?size=300x300&data=https://t.me/rodwell_portal_password_bot?start=T4T9K9TF87D8MW3K",
    "expiresAt": "2025-08-20T09:35:40.589Z"
  },
  {
    "studentId": "RQKNhoVoLmTM01oIaBWA",
    "studentName": "Leang Lier",
    "username": "N/A",
    "class": "Class 12S",
    "token": "T5KSDHMK3MYESH56",
    "qrCodeURL": "https://api.qrserver.com/v1/create-qr-code/?size=300x300&data=https://t.me/rodwell_portal_password_bot?start=T5KSDHMK3MYESH56",
    "expiresAt": "2025-08-20T09:35:40.589Z"
  },
  {
    "studentId": "RTcWCR8ZaMJaaQ6rNppD",
    "studentName": "Thiounn Panhabot",
    "username": "N/A",
    "class": "Class 12M",
    "token": "976GPP66BYM63CAH",
    "qrCodeURL": "https://api.qrserver.com/v1/create-qr-code/?size=300x300&data=https://t.me/rodwell_portal_password_bot?start=976GPP66BYM63CAH",
    "expiresAt": "2025-08-20T09:35:40.589Z"
  },
  {
    "studentId": "ReLs04a81mVCxmtFuqTG",
    "studentName": "Hang ChanLinda",
    "username": "N/A",
    "class": "Class 12S",
    "token": "CGFHUSX2ZNX53HKG",
    "qrCodeURL": "https://api.qrserver.com/v1/create-qr-code/?size=300x300&data=https://t.me/rodwell_portal_password_bot?start=CGFHUSX2ZNX53HKG",
    "expiresAt": "2025-08-20T09:35:40.589Z"
  },
  {
    "studentId": "RjmK5kXwrg2BwEux0KgZ",
    "studentName": "Chhun SokkumMongkol",
    "username": "N/A",
    "class": "Class 9E",
    "token": "52GDZBFC2RAJYMKP",
    "qrCodeURL": "https://api.qrserver.com/v1/create-qr-code/?size=300x300&data=https://t.me/rodwell_portal_password_bot?start=52GDZBFC2RAJYMKP",
    "expiresAt": "2025-08-20T09:35:40.589Z"
  },
  {
    "studentId": "RnCz35c8tzUA0crN2pQb",
    "studentName": "Cha Channaroth",
    "username": "N/A",
    "class": "Class 10F",
    "token": "8YQ8E7R65KRUBHFP",
    "qrCodeURL": "https://api.qrserver.com/v1/create-qr-code/?size=300x300&data=https://t.me/rodwell_portal_password_bot?start=8YQ8E7R65KRUBHFP",
    "expiresAt": "2025-08-20T09:35:40.589Z"
  },
  {
    "studentId": "SDRyQCwOVCoSf2bk48M9",
    "studentName": "Sam Sopheakneary",
    "username": "N/A",
    "class": "Class 8E",
    "token": "H5MX8CGZ4JSB6AMH",
    "qrCodeURL": "https://api.qrserver.com/v1/create-qr-code/?size=300x300&data=https://t.me/rodwell_portal_password_bot?start=H5MX8CGZ4JSB6AMH",
    "expiresAt": "2025-08-20T09:35:40.589Z"
  },
  {
    "studentId": "SOBB6EnFiie5EWQ6ASOU",
    "studentName": "Sok Chanpheary",
    "username": "N/A",
    "class": "Class 11E",
    "token": "55HVA4NLRCWZ6MDY",
    "qrCodeURL": "https://api.qrserver.com/v1/create-qr-code/?size=300x300&data=https://t.me/rodwell_portal_password_bot?start=55HVA4NLRCWZ6MDY",
    "expiresAt": "2025-08-20T09:35:40.589Z"
  },
  {
    "studentId": "SsR39bEAXYFWORaPBKBY",
    "studentName": "Bourvann Phary",
    "username": "N/A",
    "class": "Class 12C",
    "token": "Q47HZC3W2882CA3Y",
    "qrCodeURL": "https://api.qrserver.com/v1/create-qr-code/?size=300x300&data=https://t.me/rodwell_portal_password_bot?start=Q47HZC3W2882CA3Y",
    "expiresAt": "2025-08-20T09:35:40.589Z"
  },
  {
    "studentId": "T47c65TROk5BaOKKGBrF",
    "studentName": "Kouch Mouyleng",
    "username": "N/A",
    "class": "Class 11A",
    "token": "6HKNST3FBZXCFETW",
    "qrCodeURL": "https://api.qrserver.com/v1/create-qr-code/?size=300x300&data=https://t.me/rodwell_portal_password_bot?start=6HKNST3FBZXCFETW",
    "expiresAt": "2025-08-20T09:35:40.589Z"
  },
  {
    "studentId": "TjICeZHumdrCHNLzkqlx",
    "studentName": "Heng Kimseng",
    "username": "N/A",
    "class": "Class 12C",
    "token": "ZVR67JZ8HALJPPSZ",
    "qrCodeURL": "https://api.qrserver.com/v1/create-qr-code/?size=300x300&data=https://t.me/rodwell_portal_password_bot?start=ZVR67JZ8HALJPPSZ",
    "expiresAt": "2025-08-20T09:35:40.589Z"
  },
  {
    "studentId": "Us2iBBRcH5sSJ1yOxB9V",
    "studentName": "Mov Kokhour",
    "username": "N/A",
    "class": "Class 10F",
    "token": "SM42LALTPPD7FNDK",
    "qrCodeURL": "https://api.qrserver.com/v1/create-qr-code/?size=300x300&data=https://t.me/rodwell_portal_password_bot?start=SM42LALTPPD7FNDK",
    "expiresAt": "2025-08-20T09:35:40.589Z"
  },
  {
    "studentId": "VHBo6RDrl4elU80bZc5H",
    "studentName": "Oeur Mengyu",
    "username": "N/A",
    "class": "Class 10F",
    "token": "DU2BAQC64TNMQCPY",
    "qrCodeURL": "https://api.qrserver.com/v1/create-qr-code/?size=300x300&data=https://t.me/rodwell_portal_password_bot?start=DU2BAQC64TNMQCPY",
    "expiresAt": "2025-08-20T09:35:40.589Z"
  },
  {
    "studentId": "VRfZsQPoQSOEmeAFqLjC",
    "studentName": "Chhour Sokkhim",
    "username": "N/A",
    "class": "Class 12M",
    "token": "SNYN4ZZ2EVR24ND3",
    "qrCodeURL": "https://api.qrserver.com/v1/create-qr-code/?size=300x300&data=https://t.me/rodwell_portal_password_bot?start=SNYN4ZZ2EVR24ND3",
    "expiresAt": "2025-08-20T09:35:40.589Z"
  },
  {
    "studentId": "VfSK796y4rAiDx0KOdcw",
    "studentName": "Hong Chengkeang",
    "username": "N/A",
    "class": "Class 11E",
    "token": "RLZGWVND7HMMELUL",
    "qrCodeURL": "https://api.qrserver.com/v1/create-qr-code/?size=300x300&data=https://t.me/rodwell_portal_password_bot?start=RLZGWVND7HMMELUL",
    "expiresAt": "2025-08-20T09:35:40.589Z"
  },
  {
    "studentId": "VxzqXXjevyPvoMKKTShI",
    "studentName": "Kheav MengLeang",
    "username": "N/A",
    "class": "Class 12S",
    "token": "EA6MQ7L6DBDXD6FZ",
    "qrCodeURL": "https://api.qrserver.com/v1/create-qr-code/?size=300x300&data=https://t.me/rodwell_portal_password_bot?start=EA6MQ7L6DBDXD6FZ",
    "expiresAt": "2025-08-20T09:35:40.589Z"
  },
  {
    "studentId": "W5qazT2WrNnubEbryRMQ",
    "studentName": "Reth Nypheareach",
    "username": "N/A",
    "class": "Class 10E",
    "token": "HMGGJRRELDVK2ZQK",
    "qrCodeURL": "https://api.qrserver.com/v1/create-qr-code/?size=300x300&data=https://t.me/rodwell_portal_password_bot?start=HMGGJRRELDVK2ZQK",
    "expiresAt": "2025-08-20T09:35:40.589Z"
  },
  {
    "studentId": "WEYupDDQbogpH90YPJwY",
    "studentName": "Nhem Daramoon",
    "username": "N/A",
    "class": "Class 12C",
    "token": "P6ZEH522SP23R6TX",
    "qrCodeURL": "https://api.qrserver.com/v1/create-qr-code/?size=300x300&data=https://t.me/rodwell_portal_password_bot?start=P6ZEH522SP23R6TX",
    "expiresAt": "2025-08-20T09:35:40.589Z"
  },
  {
    "studentId": "WuLtHTeVcWzzYZj5ZIks",
    "studentName": "Sou Saprina",
    "username": "N/A",
    "class": "Class 12I",
    "token": "LHLM6BLZJAC2UY3J",
    "qrCodeURL": "https://api.qrserver.com/v1/create-qr-code/?size=300x300&data=https://t.me/rodwell_portal_password_bot?start=LHLM6BLZJAC2UY3J",
    "expiresAt": "2025-08-20T09:35:40.589Z"
  },
  {
    "studentId": "X4uGqcONHz3mUdvATzTE",
    "studentName": "Phorn Sorina",
    "username": "N/A",
    "class": "Class 12M",
    "token": "YJ9DXYQRGRDG3YVZ",
    "qrCodeURL": "https://api.qrserver.com/v1/create-qr-code/?size=300x300&data=https://t.me/rodwell_portal_password_bot?start=YJ9DXYQRGRDG3YVZ",
    "expiresAt": "2025-08-20T09:35:40.589Z"
  },
  {
    "studentId": "XNPYpt4qIdXu4OUIWY9U",
    "studentName": "Dy Danana",
    "username": "N/A",
    "class": "Class 12C",
    "token": "T2DWD9VTBFGSATVT",
    "qrCodeURL": "https://api.qrserver.com/v1/create-qr-code/?size=300x300&data=https://t.me/rodwell_portal_password_bot?start=T2DWD9VTBFGSATVT",
    "expiresAt": "2025-08-20T09:35:40.589Z"
  },
  {
    "studentId": "XNWzNkZHFnRLGSV6hFEh",
    "studentName": "Chhea Vortey",
    "username": "N/A",
    "class": "Class 12C",
    "token": "DBN8EUNQB6WXCQTK",
    "qrCodeURL": "https://api.qrserver.com/v1/create-qr-code/?size=300x300&data=https://t.me/rodwell_portal_password_bot?start=DBN8EUNQB6WXCQTK",
    "expiresAt": "2025-08-20T09:35:40.589Z"
  },
  {
    "studentId": "YaHOsOeB2G4hcZPTVail",
    "studentName": "Nilkeaw Phatharakphorn",
    "username": "N/A",
    "class": "Class 9F",
    "token": "VKK8WXE33RQ48RLR",
    "qrCodeURL": "https://api.qrserver.com/v1/create-qr-code/?size=300x300&data=https://t.me/rodwell_portal_password_bot?start=VKK8WXE33RQ48RLR",
    "expiresAt": "2025-08-20T09:35:40.589Z"
  },
  {
    "studentId": "ZsHj0iB9e4iKWaCy39L3",
    "studentName": "Khun Soktin",
    "username": "N/A",
    "class": "Class 12I",
    "token": "GCMZRNSWC6UQ8QC2",
    "qrCodeURL": "https://api.qrserver.com/v1/create-qr-code/?size=300x300&data=https://t.me/rodwell_portal_password_bot?start=GCMZRNSWC6UQ8QC2",
    "expiresAt": "2025-08-20T09:35:40.589Z"
  },
  {
    "studentId": "aFuSVJROTLEjiyAp80uz",
    "studentName": "Thik Yalina",
    "username": "N/A",
    "class": "Class 12E",
    "token": "MJGKEY3CW7ZE8DMF",
    "qrCodeURL": "https://api.qrserver.com/v1/create-qr-code/?size=300x300&data=https://t.me/rodwell_portal_password_bot?start=MJGKEY3CW7ZE8DMF",
    "expiresAt": "2025-08-20T09:35:40.589Z"
  },
  {
    "studentId": "abonKvvYCfgHBEIubX8R",
    "studentName": "Leng Longhak",
    "username": "N/A",
    "class": "Class 8E",
    "token": "AVPV7228ZRZ28748",
    "qrCodeURL": "https://api.qrserver.com/v1/create-qr-code/?size=300x300&data=https://t.me/rodwell_portal_password_bot?start=AVPV7228ZRZ28748",
    "expiresAt": "2025-08-20T09:35:40.590Z"
  },
  {
    "studentId": "awEaDHHoPdbDkyNQ2WQm",
    "studentName": "Kong Hannlong",
    "username": "N/A",
    "class": "Class 11E",
    "token": "539KLBEPTRWFPV69",
    "qrCodeURL": "https://api.qrserver.com/v1/create-qr-code/?size=300x300&data=https://t.me/rodwell_portal_password_bot?start=539KLBEPTRWFPV69",
    "expiresAt": "2025-08-20T09:35:40.590Z"
  },
  {
    "studentId": "bMRCXDFb4ONNyP5uAl9t",
    "studentName": "Chhuon Sereyvath",
    "username": "N/A",
    "class": "Class 12E",
    "token": "FVY77H98JGVWVHVL",
    "qrCodeURL": "https://api.qrserver.com/v1/create-qr-code/?size=300x300&data=https://t.me/rodwell_portal_password_bot?start=FVY77H98JGVWVHVL",
    "expiresAt": "2025-08-20T09:35:40.590Z"
  },
  {
    "studentId": "bf0wTuwEk7nhHg7oEGHy",
    "studentName": "Sum Kimlay",
    "username": "N/A",
    "class": "Class 12C",
    "token": "46PMRFQXEWWXM7M5",
    "qrCodeURL": "https://api.qrserver.com/v1/create-qr-code/?size=300x300&data=https://t.me/rodwell_portal_password_bot?start=46PMRFQXEWWXM7M5",
    "expiresAt": "2025-08-20T09:35:40.590Z"
  },
  {
    "studentId": "bjnMLHcH32fIugkPlzBV",
    "studentName": "Kannari Megumi",
    "username": "N/A",
    "class": "Class 12E",
    "token": "5T3QQJEWMBA63967",
    "qrCodeURL": "https://api.qrserver.com/v1/create-qr-code/?size=300x300&data=https://t.me/rodwell_portal_password_bot?start=5T3QQJEWMBA63967",
    "expiresAt": "2025-08-20T09:35:40.590Z"
  },
  {
    "studentId": "cPpJb1XCs7vb5cIX4DFj",
    "studentName": "So Sovanda",
    "username": "N/A",
    "class": "Class 12I",
    "token": "EKAGYHUUCWDPLBBH",
    "qrCodeURL": "https://api.qrserver.com/v1/create-qr-code/?size=300x300&data=https://t.me/rodwell_portal_password_bot?start=EKAGYHUUCWDPLBBH",
    "expiresAt": "2025-08-20T09:35:40.590Z"
  },
  {
    "studentId": "ceoFJuqp4Ym09LelGFpo",
    "studentName": "Lak Bunhour",
    "username": "N/A",
    "class": "Class 10E",
    "token": "B6HGBKV8M7TJUHAA",
    "qrCodeURL": "https://api.qrserver.com/v1/create-qr-code/?size=300x300&data=https://t.me/rodwell_portal_password_bot?start=B6HGBKV8M7TJUHAA",
    "expiresAt": "2025-08-20T09:35:40.590Z"
  },
  {
    "studentId": "cjvXUIdQqpx3tRsHd9Ks",
    "studentName": "Seng Chansocheat",
    "username": "N/A",
    "class": "Class 10F",
    "token": "NWJ6LU5AQ37HA82D",
    "qrCodeURL": "https://api.qrserver.com/v1/create-qr-code/?size=300x300&data=https://t.me/rodwell_portal_password_bot?start=NWJ6LU5AQ37HA82D",
    "expiresAt": "2025-08-20T09:35:40.590Z"
  },
  {
    "studentId": "cpAcoWSdZDr4awyrjJnH",
    "studentName": "Kim KeoSokunpidor",
    "username": "N/A",
    "class": "Class 12C",
    "token": "ZTR3WEM5WUPH3S5Q",
    "qrCodeURL": "https://api.qrserver.com/v1/create-qr-code/?size=300x300&data=https://t.me/rodwell_portal_password_bot?start=ZTR3WEM5WUPH3S5Q",
    "expiresAt": "2025-08-20T09:35:40.590Z"
  },
  {
    "studentId": "d6eGhtcPVOXWV2Ausilk",
    "studentName": "Dy Sreypich",
    "username": "N/A",
    "class": "Class 9E",
    "token": "VUSWJ5W27ECYB2KA",
    "qrCodeURL": "https://api.qrserver.com/v1/create-qr-code/?size=300x300&data=https://t.me/rodwell_portal_password_bot?start=VUSWJ5W27ECYB2KA",
    "expiresAt": "2025-08-20T09:35:40.590Z"
  },
  {
    "studentId": "d6pvQ5s7HP8DbPvP9pC4",
    "studentName": "Heng ChendaVattey",
    "username": "N/A",
    "class": "Class 12S",
    "token": "VQUUFQA49R77KRM3",
    "qrCodeURL": "https://api.qrserver.com/v1/create-qr-code/?size=300x300&data=https://t.me/rodwell_portal_password_bot?start=VQUUFQA49R77KRM3",
    "expiresAt": "2025-08-20T09:35:40.590Z"
  },
  {
    "studentId": "d7RA2ke7GUdYvTACTtKM",
    "studentName": "Tep Sophireak",
    "username": "N/A",
    "class": "Class 12I",
    "token": "LRBNEJJX55AUM43C",
    "qrCodeURL": "https://api.qrserver.com/v1/create-qr-code/?size=300x300&data=https://t.me/rodwell_portal_password_bot?start=LRBNEJJX55AUM43C",
    "expiresAt": "2025-08-20T09:35:40.590Z"
  },
  {
    "studentId": "dSPG1f4pEMPoKLXSxzFX",
    "studentName": "Mich Rothana",
    "username": "N/A",
    "class": "Class 12E",
    "token": "8AZT2GJUU7UCLA6V",
    "qrCodeURL": "https://api.qrserver.com/v1/create-qr-code/?size=300x300&data=https://t.me/rodwell_portal_password_bot?start=8AZT2GJUU7UCLA6V",
    "expiresAt": "2025-08-20T09:35:40.590Z"
  },
  {
    "studentId": "eDlqns0LpgVRqWow2oKb",
    "studentName": "Yit SreyLeak",
    "username": "N/A",
    "class": "Class 12S",
    "token": "DZXGCX45Y29B9ZYP",
    "qrCodeURL": "https://api.qrserver.com/v1/create-qr-code/?size=300x300&data=https://t.me/rodwell_portal_password_bot?start=DZXGCX45Y29B9ZYP",
    "expiresAt": "2025-08-20T09:35:40.590Z"
  },
  {
    "studentId": "eIdrgXEva57SRdPlKmZx",
    "studentName": "Run MonyKeo",
    "username": "N/A",
    "class": "Class 12I",
    "token": "C5WJMMCJK3QCSVR5",
    "qrCodeURL": "https://api.qrserver.com/v1/create-qr-code/?size=300x300&data=https://t.me/rodwell_portal_password_bot?start=C5WJMMCJK3QCSVR5",
    "expiresAt": "2025-08-20T09:35:40.590Z"
  },
  {
    "studentId": "eM6tgEf50Ay0RKOH6TIl",
    "studentName": "Morng Rotanak",
    "username": "N/A",
    "class": "Class 12C",
    "token": "GG598EANP9N9384P",
    "qrCodeURL": "https://api.qrserver.com/v1/create-qr-code/?size=300x300&data=https://t.me/rodwell_portal_password_bot?start=GG598EANP9N9384P",
    "expiresAt": "2025-08-20T09:35:40.590Z"
  },
  {
    "studentId": "eN67xF9rgxzVxSOTIzZ8",
    "studentName": "Horn Outdom",
    "username": "N/A",
    "class": "Class 12M",
    "token": "HTTT7RYD588C9P8P",
    "qrCodeURL": "https://api.qrserver.com/v1/create-qr-code/?size=300x300&data=https://t.me/rodwell_portal_password_bot?start=HTTT7RYD588C9P8P",
    "expiresAt": "2025-08-20T09:35:40.590Z"
  },
  {
    "studentId": "eOdgOzC1gxWeGjME65r4",
    "studentName": "Eang Lucent",
    "username": "N/A",
    "class": "Class 12I",
    "token": "FRXXQDMEL3236ADV",
    "qrCodeURL": "https://api.qrserver.com/v1/create-qr-code/?size=300x300&data=https://t.me/rodwell_portal_password_bot?start=FRXXQDMEL3236ADV",
    "expiresAt": "2025-08-20T09:35:40.590Z"
  },
  {
    "studentId": "egpRO5cUEKoNatJjz1jp",
    "studentName": "Sokha Arenchentra",
    "username": "N/A",
    "class": "Class 7E",
    "token": "LT9S4PFJDPP55F36",
    "qrCodeURL": "https://api.qrserver.com/v1/create-qr-code/?size=300x300&data=https://t.me/rodwell_portal_password_bot?start=LT9S4PFJDPP55F36",
    "expiresAt": "2025-08-20T09:35:40.590Z"
  },
  {
    "studentId": "eosdDrEL4FGz4yjg003V",
    "studentName": "Heang Ratanachan",
    "username": "N/A",
    "class": "Class 8E",
    "token": "JRWA2KKPEBXACJ3T",
    "qrCodeURL": "https://api.qrserver.com/v1/create-qr-code/?size=300x300&data=https://t.me/rodwell_portal_password_bot?start=JRWA2KKPEBXACJ3T",
    "expiresAt": "2025-08-20T09:35:40.590Z"
  },
  {
    "studentId": "fFquVV2O7MqGcS3kryiM",
    "studentName": "Sor Sivly",
    "username": "N/A",
    "class": "Class 11A",
    "token": "RU4DDZGNHULMEMGQ",
    "qrCodeURL": "https://api.qrserver.com/v1/create-qr-code/?size=300x300&data=https://t.me/rodwell_portal_password_bot?start=RU4DDZGNHULMEMGQ",
    "expiresAt": "2025-08-20T09:35:40.590Z"
  },
  {
    "studentId": "fxzWt3UUl631phBfbpJq",
    "studentName": "Khun Vensing",
    "username": "N/A",
    "class": "Class 12I",
    "token": "KPV9GM9MEMZ8USUW",
    "qrCodeURL": "https://api.qrserver.com/v1/create-qr-code/?size=300x300&data=https://t.me/rodwell_portal_password_bot?start=KPV9GM9MEMZ8USUW",
    "expiresAt": "2025-08-20T09:35:40.590Z"
  },
  {
    "studentId": "gEjMKyok7FgRr9sdpGQI",
    "studentName": "Chung ChangPhengAnn",
    "username": "N/A",
    "class": "Class 12S",
    "token": "QFUJ8LGUUBGYXCXW",
    "qrCodeURL": "https://api.qrserver.com/v1/create-qr-code/?size=300x300&data=https://t.me/rodwell_portal_password_bot?start=QFUJ8LGUUBGYXCXW",
    "expiresAt": "2025-08-20T09:35:40.590Z"
  },
  {
    "studentId": "h2DQ9pKSS7BDtSMNbx34",
    "studentName": "Ket Phallika",
    "username": "N/A",
    "class": "Class 12S",
    "token": "B35LAPR2Q2QBHSFQ",
    "qrCodeURL": "https://api.qrserver.com/v1/create-qr-code/?size=300x300&data=https://t.me/rodwell_portal_password_bot?start=B35LAPR2Q2QBHSFQ",
    "expiresAt": "2025-08-20T09:35:40.590Z"
  },
  {
    "studentId": "h9atyDlHVHH9f5qlePf3",
    "studentName": "Samith Soeunghaksenna",
    "username": "N/A",
    "class": "Class 12NKGS",
    "token": "5PGAGUWEU4TSWZED",
    "qrCodeURL": "https://api.qrserver.com/v1/create-qr-code/?size=300x300&data=https://t.me/rodwell_portal_password_bot?start=5PGAGUWEU4TSWZED",
    "expiresAt": "2025-08-20T09:35:40.590Z"
  },
  {
    "studentId": "hBCrUyRTQh2pG2KnPnzW",
    "studentName": "Po Chanrattanak",
    "username": "N/A",
    "class": "Class 12E",
    "token": "JDY6MYVBHJ8GFYH5",
    "qrCodeURL": "https://api.qrserver.com/v1/create-qr-code/?size=300x300&data=https://t.me/rodwell_portal_password_bot?start=JDY6MYVBHJ8GFYH5",
    "expiresAt": "2025-08-20T09:35:40.590Z"
  },
  {
    "studentId": "hOLM7PxbBd8yJawPitBY",
    "studentName": "Heng Panhasoth",
    "username": "N/A",
    "class": "Class 12C",
    "token": "W7QVQWKDLK4KNPKK",
    "qrCodeURL": "https://api.qrserver.com/v1/create-qr-code/?size=300x300&data=https://t.me/rodwell_portal_password_bot?start=W7QVQWKDLK4KNPKK",
    "expiresAt": "2025-08-20T09:35:40.590Z"
  },
  {
    "studentId": "hZ07uzbVu2QnzIR5ipFP",
    "studentName": "Rou Sodaphinun",
    "username": "N/A",
    "class": "Class 8E",
    "token": "CRS7L75U7GXQTAKA",
    "qrCodeURL": "https://api.qrserver.com/v1/create-qr-code/?size=300x300&data=https://t.me/rodwell_portal_password_bot?start=CRS7L75U7GXQTAKA",
    "expiresAt": "2025-08-20T09:35:40.590Z"
  },
  {
    "studentId": "hcZtzF7XECemYPtz8ED3",
    "studentName": "Rath Sopheakleap",
    "username": "N/A",
    "class": "Class 12E",
    "token": "ZPZ53N3583X28PSX",
    "qrCodeURL": "https://api.qrserver.com/v1/create-qr-code/?size=300x300&data=https://t.me/rodwell_portal_password_bot?start=ZPZ53N3583X28PSX",
    "expiresAt": "2025-08-20T09:35:40.590Z"
  },
  {
    "studentId": "hvPHY9nLSmfMhRMw4oQw",
    "studentName": "Nut Tymoeung",
    "username": "N/A",
    "class": "Class 12E",
    "token": "LYDX3SJJLSZN8SK4",
    "qrCodeURL": "https://api.qrserver.com/v1/create-qr-code/?size=300x300&data=https://t.me/rodwell_portal_password_bot?start=LYDX3SJJLSZN8SK4",
    "expiresAt": "2025-08-20T09:35:40.590Z"
  },
  {
    "studentId": "hzKJ0wqeUQ1sVNDyn2Jw",
    "studentName": "Chey Norin",
    "username": "N/A",
    "class": "Class 12C",
    "token": "ZRWAAFZDNEXCBRB4",
    "qrCodeURL": "https://api.qrserver.com/v1/create-qr-code/?size=300x300&data=https://t.me/rodwell_portal_password_bot?start=ZRWAAFZDNEXCBRB4",
    "expiresAt": "2025-08-20T09:35:40.590Z"
  },
  {
    "studentId": "is6gTf0lmACJP2UlrO5A",
    "studentName": "Phol Sophana",
    "username": "N/A",
    "class": "Class 11E",
    "token": "WV64HJK63D24EQ6Q",
    "qrCodeURL": "https://api.qrserver.com/v1/create-qr-code/?size=300x300&data=https://t.me/rodwell_portal_password_bot?start=WV64HJK63D24EQ6Q",
    "expiresAt": "2025-08-20T09:35:40.590Z"
  },
  {
    "studentId": "j2ZZu7iVxI8hiDEzy6Z7",
    "studentName": "Chhen Chanlyza",
    "username": "N/A",
    "class": "Class 12I",
    "token": "PRDCVAP275B23G4W",
    "qrCodeURL": "https://api.qrserver.com/v1/create-qr-code/?size=300x300&data=https://t.me/rodwell_portal_password_bot?start=PRDCVAP275B23G4W",
    "expiresAt": "2025-08-20T09:35:40.591Z"
  },
  {
    "studentId": "kJWytP3KTcQMd8WIFODE",
    "studentName": "Nai Vireakpitou",
    "username": "N/A",
    "class": "Class 12E",
    "token": "G6UK2S6UW2RANFTU",
    "qrCodeURL": "https://api.qrserver.com/v1/create-qr-code/?size=300x300&data=https://t.me/rodwell_portal_password_bot?start=G6UK2S6UW2RANFTU",
    "expiresAt": "2025-08-20T09:35:40.591Z"
  },
  {
    "studentId": "kQWUwqJwjZPSX6FPdPQE",
    "studentName": "Seng Sumethy",
    "username": "N/A",
    "class": "Class 9F",
    "token": "VATZGVA3Y2WJ53TT",
    "qrCodeURL": "https://api.qrserver.com/v1/create-qr-code/?size=300x300&data=https://t.me/rodwell_portal_password_bot?start=VATZGVA3Y2WJ53TT",
    "expiresAt": "2025-08-20T09:35:40.591Z"
  },
  {
    "studentId": "kU9gs4JfojluxFlYMO0D",
    "studentName": "Suor Puthitheavy",
    "username": "N/A",
    "class": "Class 12E",
    "token": "C5HJTLGD3MZ2LJ8S",
    "qrCodeURL": "https://api.qrserver.com/v1/create-qr-code/?size=300x300&data=https://t.me/rodwell_portal_password_bot?start=C5HJTLGD3MZ2LJ8S",
    "expiresAt": "2025-08-20T09:35:40.591Z"
  },
  {
    "studentId": "khqcjiykmPG4dK3DDU3G",
    "studentName": "No Ratanaboth",
    "username": "N/A",
    "class": "Class 11E",
    "token": "BUA5R9XZZ6H9L7PY",
    "qrCodeURL": "https://api.qrserver.com/v1/create-qr-code/?size=300x300&data=https://t.me/rodwell_portal_password_bot?start=BUA5R9XZZ6H9L7PY",
    "expiresAt": "2025-08-20T09:35:40.591Z"
  },
  {
    "studentId": "l9ze7YCAqgSvT3cas70J",
    "studentName": "Ly Chantheng",
    "username": "N/A",
    "class": "Class 12C",
    "token": "BQTTSQHT6XENT2VU",
    "qrCodeURL": "https://api.qrserver.com/v1/create-qr-code/?size=300x300&data=https://t.me/rodwell_portal_password_bot?start=BQTTSQHT6XENT2VU",
    "expiresAt": "2025-08-20T09:35:40.591Z"
  },
  {
    "studentId": "lLuUkIavAV9PozBsStt0",
    "studentName": "Kea Danita",
    "username": "N/A",
    "class": "Class 12C",
    "token": "MLZHYWAZJPX2XQG4",
    "qrCodeURL": "https://api.qrserver.com/v1/create-qr-code/?size=300x300&data=https://t.me/rodwell_portal_password_bot?start=MLZHYWAZJPX2XQG4",
    "expiresAt": "2025-08-20T09:35:40.591Z"
  },
  {
    "studentId": "ln1YPLOdHXYYU6uEQrFN",
    "studentName": "Lim Geachleap",
    "username": "N/A",
    "class": "Class 12M",
    "token": "AFGCLGZ9ZSBBJPQ6",
    "qrCodeURL": "https://api.qrserver.com/v1/create-qr-code/?size=300x300&data=https://t.me/rodwell_portal_password_bot?start=AFGCLGZ9ZSBBJPQ6",
    "expiresAt": "2025-08-20T09:35:40.591Z"
  },
  {
    "studentId": "lsIXsqFMJj1o4R80GC6G",
    "studentName": "Tang Uynam",
    "username": "N/A",
    "class": "Class 8E",
    "token": "AK573WV6H999PZAY",
    "qrCodeURL": "https://api.qrserver.com/v1/create-qr-code/?size=300x300&data=https://t.me/rodwell_portal_password_bot?start=AK573WV6H999PZAY",
    "expiresAt": "2025-08-20T09:35:40.591Z"
  },
  {
    "studentId": "n9pLtUPGtwPwMABEzjy8",
    "studentName": "Tang PichLyka",
    "username": "N/A",
    "class": "Class 12I",
    "token": "EB2Y6S6WKCY8W5J3",
    "qrCodeURL": "https://api.qrserver.com/v1/create-qr-code/?size=300x300&data=https://t.me/rodwell_portal_password_bot?start=EB2Y6S6WKCY8W5J3",
    "expiresAt": "2025-08-20T09:35:40.591Z"
  },
  {
    "studentId": "nMsg2tuab5ki3kPbolDT",
    "studentName": "Ouk Rithryhana",
    "username": "N/A",
    "class": "Class 9F",
    "token": "YZ66QW2RDHM87D7F",
    "qrCodeURL": "https://api.qrserver.com/v1/create-qr-code/?size=300x300&data=https://t.me/rodwell_portal_password_bot?start=YZ66QW2RDHM87D7F",
    "expiresAt": "2025-08-20T09:35:40.591Z"
  },
  {
    "studentId": "nNUe4Ou6No4VNj2PjocZ",
    "studentName": "Chinda Vouchly",
    "username": "N/A",
    "class": "Class 12C",
    "token": "58DQTL3ZZPKHQAJQ",
    "qrCodeURL": "https://api.qrserver.com/v1/create-qr-code/?size=300x300&data=https://t.me/rodwell_portal_password_bot?start=58DQTL3ZZPKHQAJQ",
    "expiresAt": "2025-08-20T09:35:40.591Z"
  },
  {
    "studentId": "nVFlhctujk9qmbLtRTff",
    "studentName": "Huy Sovichar",
    "username": "N/A",
    "class": "Class 12C",
    "token": "YJJ62836HJ25EBXN",
    "qrCodeURL": "https://api.qrserver.com/v1/create-qr-code/?size=300x300&data=https://t.me/rodwell_portal_password_bot?start=YJJ62836HJ25EBXN",
    "expiresAt": "2025-08-20T09:35:40.591Z"
  },
  {
    "studentId": "oFSJhTfNxlRpuiG1oELU",
    "studentName": "Chun Ek",
    "username": "N/A",
    "class": "Class 12E",
    "token": "T2ANP95H3DAV2Y6H",
    "qrCodeURL": "https://api.qrserver.com/v1/create-qr-code/?size=300x300&data=https://t.me/rodwell_portal_password_bot?start=T2ANP95H3DAV2Y6H",
    "expiresAt": "2025-08-20T09:35:40.591Z"
  },
  {
    "studentId": "oHHWmDGCoZywoi7EW1DY",
    "studentName": "Hem Chanvichea",
    "username": "N/A",
    "class": "Class 12I",
    "token": "AP7S2G9N7HHRZMM5",
    "qrCodeURL": "https://api.qrserver.com/v1/create-qr-code/?size=300x300&data=https://t.me/rodwell_portal_password_bot?start=AP7S2G9N7HHRZMM5",
    "expiresAt": "2025-08-20T09:35:40.591Z"
  },
  {
    "studentId": "oXtWM7DJ8WU51sRMz3SC",
    "studentName": "Ly ReakSatevi",
    "username": "N/A",
    "class": "Class 12C",
    "token": "LKGUMTQNTLSETDLH",
    "qrCodeURL": "https://api.qrserver.com/v1/create-qr-code/?size=300x300&data=https://t.me/rodwell_portal_password_bot?start=LKGUMTQNTLSETDLH",
    "expiresAt": "2025-08-20T09:35:40.591Z"
  },
  {
    "studentId": "obshexEsX9Qpc9PssYoR",
    "studentName": "Eap Kimlyza",
    "username": "N/A",
    "class": "Class 12S",
    "token": "GQ5GLRRLUVR7JXYY",
    "qrCodeURL": "https://api.qrserver.com/v1/create-qr-code/?size=300x300&data=https://t.me/rodwell_portal_password_bot?start=GQ5GLRRLUVR7JXYY",
    "expiresAt": "2025-08-20T09:35:40.591Z"
  },
  {
    "studentId": "ogS4OANa2vLiKUiuHekZ",
    "studentName": "Chea Sivmey",
    "username": "N/A",
    "class": "Class 12M",
    "token": "KDDL6SEPFQSJSZTP",
    "qrCodeURL": "https://api.qrserver.com/v1/create-qr-code/?size=300x300&data=https://t.me/rodwell_portal_password_bot?start=KDDL6SEPFQSJSZTP",
    "expiresAt": "2025-08-20T09:35:40.591Z"
  },
  {
    "studentId": "oybTXQ1muBcMBvp0xAlJ",
    "studentName": "Chamroeun Chantraboth",
    "username": "N/A",
    "class": "Class 12E",
    "token": "BJVRUGBQWHC6GAVW",
    "qrCodeURL": "https://api.qrserver.com/v1/create-qr-code/?size=300x300&data=https://t.me/rodwell_portal_password_bot?start=BJVRUGBQWHC6GAVW",
    "expiresAt": "2025-08-20T09:35:40.591Z"
  },
  {
    "studentId": "pH4pwbYgTyoo0ws98Jhk",
    "studentName": "Tang Chhivly",
    "username": "N/A",
    "class": "Class 12S",
    "token": "T5MU8ADG7VWS2VNA",
    "qrCodeURL": "https://api.qrserver.com/v1/create-qr-code/?size=300x300&data=https://t.me/rodwell_portal_password_bot?start=T5MU8ADG7VWS2VNA",
    "expiresAt": "2025-08-20T09:35:40.591Z"
  },
  {
    "studentId": "pKaCsYszhJruBkGSsEhI",
    "studentName": "Pry Kimrath",
    "username": "N/A",
    "class": "Class 10F",
    "token": "2CCHB72GWTPYBESB",
    "qrCodeURL": "https://api.qrserver.com/v1/create-qr-code/?size=300x300&data=https://t.me/rodwell_portal_password_bot?start=2CCHB72GWTPYBESB",
    "expiresAt": "2025-08-20T09:35:40.591Z"
  },
  {
    "studentId": "pdztsMXCm4yKw4EKZjVt",
    "studentName": "Vuth Dykhynaruth",
    "username": "N/A",
    "class": "Class 12I",
    "token": "9NASEQVR9DZVB2QP",
    "qrCodeURL": "https://api.qrserver.com/v1/create-qr-code/?size=300x300&data=https://t.me/rodwell_portal_password_bot?start=9NASEQVR9DZVB2QP",
    "expiresAt": "2025-08-20T09:35:40.591Z"
  },
  {
    "studentId": "pm4iNwkkax4F2vhGPFQK",
    "studentName": "Orn Vichetra",
    "username": "N/A",
    "class": "Class 12I",
    "token": "F6CAMHJRBEJVHZH3",
    "qrCodeURL": "https://api.qrserver.com/v1/create-qr-code/?size=300x300&data=https://t.me/rodwell_portal_password_bot?start=F6CAMHJRBEJVHZH3",
    "expiresAt": "2025-08-20T09:35:40.591Z"
  },
  {
    "studentId": "pm9PnMX4U6vrndnIKhTQ",
    "studentName": "San Liheng",
    "username": "N/A",
    "class": "Class 12C",
    "token": "5RK9VKWB9FWPFTGS",
    "qrCodeURL": "https://api.qrserver.com/v1/create-qr-code/?size=300x300&data=https://t.me/rodwell_portal_password_bot?start=5RK9VKWB9FWPFTGS",
    "expiresAt": "2025-08-20T09:35:40.591Z"
  },
  {
    "studentId": "pxyFStt2AHkw5lufsoco",
    "studentName": "Ouk Sovanmulyka",
    "username": "N/A",
    "class": "Class 12C",
    "token": "LSX6D32G983CV85Q",
    "qrCodeURL": "https://api.qrserver.com/v1/create-qr-code/?size=300x300&data=https://t.me/rodwell_portal_password_bot?start=LSX6D32G983CV85Q",
    "expiresAt": "2025-08-20T09:35:40.591Z"
  },
  {
    "studentId": "qQuNmaz3VI1iY7THVuM7",
    "studentName": "Sam Visothirith Panha",
    "username": "N/A",
    "class": "Class 8E",
    "token": "L59ULY7VHLYBF4B4",
    "qrCodeURL": "https://api.qrserver.com/v1/create-qr-code/?size=300x300&data=https://t.me/rodwell_portal_password_bot?start=L59ULY7VHLYBF4B4",
    "expiresAt": "2025-08-20T09:35:40.591Z"
  },
  {
    "studentId": "qTaijrrT2FdM3J5sx0qC",
    "studentName": "Oeur Chanpichlyka",
    "username": "N/A",
    "class": "Class 12E",
    "token": "Z2NK6EP33FD5N3PD",
    "qrCodeURL": "https://api.qrserver.com/v1/create-qr-code/?size=300x300&data=https://t.me/rodwell_portal_password_bot?start=Z2NK6EP33FD5N3PD",
    "expiresAt": "2025-08-20T09:35:40.591Z"
  },
  {
    "studentId": "r5W39BigbH7Sk6pVBvk5",
    "studentName": "Tol KheangHeng",
    "username": "N/A",
    "class": "Class 12M",
    "token": "LVMNV369G2VGHPW6",
    "qrCodeURL": "https://api.qrserver.com/v1/create-qr-code/?size=300x300&data=https://t.me/rodwell_portal_password_bot?start=LVMNV369G2VGHPW6",
    "expiresAt": "2025-08-20T09:35:40.591Z"
  },
  {
    "studentId": "r7sSJKARyYvlAd30pm2a",
    "studentName": "Oeung Puthsovannita",
    "username": "N/A",
    "class": "Class 12I",
    "token": "388T2LD7FJTP36WP",
    "qrCodeURL": "https://api.qrserver.com/v1/create-qr-code/?size=300x300&data=https://t.me/rodwell_portal_password_bot?start=388T2LD7FJTP36WP",
    "expiresAt": "2025-08-20T09:35:40.591Z"
  },
  {
    "studentId": "r8ZuocbQUPNw6PQjWQfP",
    "studentName": "Sam Veha",
    "username": "N/A",
    "class": "Class 12I",
    "token": "T67PS8BNPTAATCFG",
    "qrCodeURL": "https://api.qrserver.com/v1/create-qr-code/?size=300x300&data=https://t.me/rodwell_portal_password_bot?start=T67PS8BNPTAATCFG",
    "expiresAt": "2025-08-20T09:35:40.591Z"
  },
  {
    "studentId": "rkAY7rWgOyWA5zleaXB5",
    "studentName": "Kim Bropey",
    "username": "N/A",
    "class": "Class 11E",
    "token": "W9U9MCUG6UPQPGQJ",
    "qrCodeURL": "https://api.qrserver.com/v1/create-qr-code/?size=300x300&data=https://t.me/rodwell_portal_password_bot?start=W9U9MCUG6UPQPGQJ",
    "expiresAt": "2025-08-20T09:35:40.591Z"
  },
  {
    "studentId": "tRqMxk9lefD9l4r6ht9H",
    "studentName": "Sovannadany Narita",
    "username": "N/A",
    "class": "Class 12C",
    "token": "E5NN5BJ8TDDZAWGM",
    "qrCodeURL": "https://api.qrserver.com/v1/create-qr-code/?size=300x300&data=https://t.me/rodwell_portal_password_bot?start=E5NN5BJ8TDDZAWGM",
    "expiresAt": "2025-08-20T09:35:40.591Z"
  },
  {
    "studentId": "uKFeT722eKpYFpGVsesr",
    "studentName": "Test Testing",
    "username": "N/A",
    "class": "Class 11A",
    "token": "DQY3W5TBAG87JQYH",
    "qrCodeURL": "https://api.qrserver.com/v1/create-qr-code/?size=300x300&data=https://t.me/rodwell_portal_password_bot?start=DQY3W5TBAG87JQYH",
    "expiresAt": "2025-08-20T09:35:40.592Z"
  },
  {
    "studentId": "uOrjQwGpB9yFRf0mi5BZ",
    "studentName": "Sin Sonice",
    "username": "N/A",
    "class": "Class 12I",
    "token": "BWFSLWVTC36DQGBH",
    "qrCodeURL": "https://api.qrserver.com/v1/create-qr-code/?size=300x300&data=https://t.me/rodwell_portal_password_bot?start=BWFSLWVTC36DQGBH",
    "expiresAt": "2025-08-20T09:35:40.592Z"
  },
  {
    "studentId": "ukvjkmfAPGlMHbpoQf9l",
    "studentName": "Ty Kun",
    "username": "N/A",
    "class": "Class 12M",
    "token": "NT5VRSXBVA4LCP8A",
    "qrCodeURL": "https://api.qrserver.com/v1/create-qr-code/?size=300x300&data=https://t.me/rodwell_portal_password_bot?start=NT5VRSXBVA4LCP8A",
    "expiresAt": "2025-08-20T09:35:40.592Z"
  },
  {
    "studentId": "vjQ38yPYZ3suxK2oqEoJ",
    "studentName": "Yean Sovanviseth",
    "username": "N/A",
    "class": "Class 12I",
    "token": "G6N976HF58STWQZ6",
    "qrCodeURL": "https://api.qrserver.com/v1/create-qr-code/?size=300x300&data=https://t.me/rodwell_portal_password_bot?start=G6N976HF58STWQZ6",
    "expiresAt": "2025-08-20T09:35:40.592Z"
  },
  {
    "studentId": "wAckME2otJGH9rvZeF0z",
    "studentName": "Seng Lykheang",
    "username": "N/A",
    "class": "Class 9F",
    "token": "JYPVXXDQ9BJCRFBH",
    "qrCodeURL": "https://api.qrserver.com/v1/create-qr-code/?size=300x300&data=https://t.me/rodwell_portal_password_bot?start=JYPVXXDQ9BJCRFBH",
    "expiresAt": "2025-08-20T09:35:40.592Z"
  },
  {
    "studentId": "wFwldiTZHUlViwUG1ITX",
    "studentName": "Buoy Sofia",
    "username": "N/A",
    "class": "Class 8E",
    "token": "BD2MHF2KXTEJ68LH",
    "qrCodeURL": "https://api.qrserver.com/v1/create-qr-code/?size=300x300&data=https://t.me/rodwell_portal_password_bot?start=BD2MHF2KXTEJ68LH",
    "expiresAt": "2025-08-20T09:35:40.592Z"
  },
  {
    "studentId": "wnTPNyHdHWRG9T9MXAvG",
    "studentName": "Eang Virakvitu",
    "username": "N/A",
    "class": "Class 10E",
    "token": "JBUZTXH8HRGL6TBR",
    "qrCodeURL": "https://api.qrserver.com/v1/create-qr-code/?size=300x300&data=https://t.me/rodwell_portal_password_bot?start=JBUZTXH8HRGL6TBR",
    "expiresAt": "2025-08-20T09:35:40.592Z"
  },
  {
    "studentId": "wrMUHu1g6Z3o8oVWSWdy",
    "studentName": "Ly Sengkeang",
    "username": "N/A",
    "class": "Class 12C",
    "token": "ERKYM2CCNV5SMMW3",
    "qrCodeURL": "https://api.qrserver.com/v1/create-qr-code/?size=300x300&data=https://t.me/rodwell_portal_password_bot?start=ERKYM2CCNV5SMMW3",
    "expiresAt": "2025-08-20T09:35:40.592Z"
  },
  {
    "studentId": "xudNSJEL5kvenLIT4hHg",
    "studentName": "Van Panharoth",
    "username": "N/A",
    "class": "Class 12E",
    "token": "BY5XP3QUK79GTNLB",
    "qrCodeURL": "https://api.qrserver.com/v1/create-qr-code/?size=300x300&data=https://t.me/rodwell_portal_password_bot?start=BY5XP3QUK79GTNLB",
    "expiresAt": "2025-08-20T09:35:40.592Z"
  },
  {
    "studentId": "y7u8iQiEBf3gv2N8k28M",
    "studentName": "Mao Solita",
    "username": "N/A",
    "class": "Class 10E",
    "token": "9DBDZPC8QTQZKG3M",
    "qrCodeURL": "https://api.qrserver.com/v1/create-qr-code/?size=300x300&data=https://t.me/rodwell_portal_password_bot?start=9DBDZPC8QTQZKG3M",
    "expiresAt": "2025-08-20T09:35:40.592Z"
  },
  {
    "studentId": "yPc1thygsKXMnIpV0NPm",
    "studentName": "Savy SereyVaddtey",
    "username": "N/A",
    "class": "Class 12C",
    "token": "6L2AC5GYYKY34ZPH",
    "qrCodeURL": "https://api.qrserver.com/v1/create-qr-code/?size=300x300&data=https://t.me/rodwell_portal_password_bot?start=6L2AC5GYYKY34ZPH",
    "expiresAt": "2025-08-20T09:35:40.592Z"
  },
  {
    "studentId": "ywwr0f5fLnwlBT9yhJ7M",
    "studentName": "Srea RattanaSonyta",
    "username": "N/A",
    "class": "Class 12I",
    "token": "VDWBYBF233VKGS5H",
    "qrCodeURL": "https://api.qrserver.com/v1/create-qr-code/?size=300x300&data=https://t.me/rodwell_portal_password_bot?start=VDWBYBF233VKGS5H",
    "expiresAt": "2025-08-20T09:35:40.592Z"
  },
  {
    "studentId": "zjqvynVR9NvtTqDSpHYZ",
    "studentName": "Ly Muyim",
    "username": "N/A",
    "class": "Class 12C",
    "token": "SFTPM8WMT3848LYU",
    "qrCodeURL": "https://api.qrserver.com/v1/create-qr-code/?size=300x300&data=https://t.me/rodwell_portal_password_bot?start=SFTPM8WMT3848LYU",
    "expiresAt": "2025-08-20T09:35:40.592Z"
  },
  {
    "studentId": "zraoypaabQKuAo7W6kwI",
    "studentName": "Lun Chansomethea",
    "username": "N/A",
    "class": "Class 12NKGS",
    "token": "3Q62EF68AP4ALPDD",
    "qrCodeURL": "https://api.qrserver.com/v1/create-qr-code/?size=300x300&data=https://t.me/rodwell_portal_password_bot?start=3Q62EF68AP4ALPDD",
    "expiresAt": "2025-08-20T09:35:40.592Z"
  },
  {
    "studentId": "zsdTWLPQPVgYC250r3vl",
    "studentName": "Chhay Sonika",
    "username": "N/A",
    "class": "Class 12I",
    "token": "KEUL5KL4KKA4GNB5",
    "qrCodeURL": "https://api.qrserver.com/v1/create-qr-code/?size=300x300&data=https://t.me/rodwell_portal_password_bot?start=KEUL5KL4KKA4GNB5",
    "expiresAt": "2025-08-20T09:35:40.592Z"
  }
]